{
  "namespaces": [
    "public"
  ],
  "name": "public",
  "tables": [
    {
      "columns": {
        "id": {
          "name": "id",
          "type": "int4",
          "unsigned": true,
          "autoincrement": true,
          "primary": true,
          "nullable": false,
          "unique": false,
          "length": null,
          "precision": 32,
          "scale": 0,
          "default": null,
          "comment": null,
          "enumItems": [],
          "mappedType": "integer"
        },
        "pedido_id": {
          "name": "pedido_id",
          "type": "int4",
          "unsigned": false,
          "autoincrement": false,
          "primary": false,
          "nullable": false,
          "unique": false,
          "length": null,
          "precision": 32,
          "scale": 0,
          "default": null,
          "comment": null,
          "enumItems": [],
          "mappedType": "integer"
        },
        "produto_id": {
          "name": "produto_id",
          "type": "int4",
          "unsigned": false,
          "autoincrement": false,
          "primary": false,
          "nullable": false,
          "unique": false,
          "length": null,
          "precision": 32,
          "scale": 0,
          "default": null,
          "comment": null,
          "enumItems": [],
          "mappedType": "integer"
        },
        "quantidade": {
          "name": "quantidade",
          "type": "int4",
          "unsigned": false,
          "autoincrement": false,
          "primary": false,
          "nullable": false,
          "unique": false,
          "length": null,
          "precision": 32,
          "scale": 0,
          "default": null,
          "comment": null,
          "enumItems": [],
          "mappedType": "integer"
        },
        "preco_unitario": {
          "name": "preco_unitario",
          "type": "int4",
          "unsigned": false,
          "autoincrement": false,
          "primary": false,
          "nullable": false,
          "unique": false,
          "length": null,
          "precision": 32,
          "scale": 0,
          "default": null,
          "comment": null,
          "enumItems": [],
          "mappedType": "integer"
        }
      },
      "name": "itemPedidos",
      "schema": "public",
      "indexes": [
        {
          "columnNames": [
            "id"
          ],
          "composite": false,
          "constraint": false,
          "keyName": "itemPedidos_pkey",
          "unique": true,
          "primary": true
        }
      ],
      "checks": [],
      "foreignKeys": {
        "itemPedidos_pedido_id_foreign": {
          "columnNames": [
            "pedido_id"
          ],
          "constraintName": "itemPedidos_pedido_id_foreign",
          "localTableName": "public.itemPedidos",
          "referencedTableName": "public.pedidos",
          "referencedColumnNames": [
            "id"
          ],
          "updateRule": "cascade",
          "deleteRule": "no action"
        },
        "itemPedidos_produto_id_foreign": {
          "columnNames": [
            "produto_id"
          ],
          "constraintName": "itemPedidos_produto_id_foreign",
          "localTableName": "public.itemPedidos",
          "referencedTableName": "public.produtos",
          "referencedColumnNames": [
            "id"
          ],
          "updateRule": "cascade",
          "deleteRule": "no action"
        }
      },
      "nativeEnums": {},
      "comment": null
    },
    {
      "columns": {
        "id": {
          "name": "id",
          "type": "int4",
          "unsigned": true,
          "autoincrement": true,
          "primary": true,
          "nullable": false,
          "unique": false,
          "length": null,
          "precision": 32,
          "scale": 0,
          "default": null,
          "comment": null,
          "enumItems": [],
          "mappedType": "integer"
        },
        "usuario_id": {
          "name": "usuario_id",
          "type": "int4",
          "unsigned": false,
          "autoincrement": false,
          "primary": false,
          "nullable": false,
          "unique": false,
          "length": null,
          "precision": 32,
          "scale": 0,
          "default": null,
          "comment": null,
          "enumItems": [],
          "mappedType": "integer"
        },
        "total": {
          "name": "total",
          "type": "int4",
          "unsigned": false,
          "autoincrement": false,
          "primary": false,
          "nullable": false,
          "unique": false,
          "length": null,
          "precision": 32,
          "scale": 0,
          "default": null,
          "comment": null,
          "enumItems": [],
          "mappedType": "integer"
        }
      },
      "name": "pedidos",
      "schema": "public",
      "indexes": [
        {
          "columnNames": [
            "id"
          ],
          "composite": false,
          "constraint": false,
          "keyName": "pedidos_pkey",
          "unique": true,
          "primary": true
        }
      ],
      "checks": [],
      "foreignKeys": {
        "pedidos_usuario_id_foreign": {
          "columnNames": [
            "usuario_id"
          ],
          "constraintName": "pedidos_usuario_id_foreign",
          "localTableName": "public.pedidos",
          "referencedTableName": "public.usuarios",
          "referencedColumnNames": [
            "id"
          ],
          "updateRule": "cascade",
          "deleteRule": "no action"
        }
      },
      "nativeEnums": {},
      "comment": null
    },
    {
      "columns": {
        "id": {
          "name": "id",
          "type": "int4",
          "unsigned": true,
          "autoincrement": true,
          "primary": true,
          "nullable": false,
          "unique": false,
          "length": null,
          "precision": 32,
          "scale": 0,
          "default": null,
          "comment": null,
          "enumItems": [],
          "mappedType": "integer"
        },
        "nome": {
          "name": "nome",
          "type": "varchar(255)",
          "unsigned": false,
          "autoincrement": false,
          "primary": false,
          "nullable": false,
          "unique": false,
          "length": 255,
          "precision": null,
          "scale": null,
          "default": null,
          "comment": null,
          "enumItems": [],
          "mappedType": "string"
        },
        "preco": {
          "name": "preco",
          "type": "int4",
          "unsigned": false,
          "autoincrement": false,
          "primary": false,
          "nullable": false,
          "unique": false,
          "length": null,
          "precision": 32,
          "scale": 0,
          "default": null,
          "comment": null,
          "enumItems": [],
          "mappedType": "integer"
        },
        "estoque": {
          "name": "estoque",
          "type": "int4",
          "unsigned": false,
          "autoincrement": false,
          "primary": false,
          "nullable": false,
          "unique": false,
          "length": null,
          "precision": 32,
          "scale": 0,
          "default": null,
          "comment": null,
          "enumItems": [],
          "mappedType": "integer"
        }
      },
      "name": "produtos",
      "schema": "public",
      "indexes": [
        {
          "columnNames": [
            "id"
          ],
          "composite": false,
          "constraint": false,
          "keyName": "produtos_pkey",
          "unique": true,
          "primary": true
        }
      ],
      "checks": [],
      "foreignKeys": {},
      "nativeEnums": {},
      "comment": null
    },
    {
      "columns": {
        "id": {
          "name": "id",
          "type": "int4",
          "unsigned": true,
          "autoincrement": true,
          "primary": true,
          "nullable": false,
          "unique": false,
          "length": null,
          "precision": 32,
          "scale": 0,
          "default": null,
          "comment": null,
          "enumItems": [],
          "mappedType": "integer"
        },
        "nome": {
          "name": "nome",
          "type": "varchar(255)",
          "unsigned": false,
          "autoincrement": false,
          "primary": false,
          "nullable": false,
          "unique": false,
          "length": 255,
          "precision": null,
          "scale": null,
          "default": null,
          "comment": null,
          "enumItems": [],
          "mappedType": "string"
        },
        "email": {
          "name": "email",
          "type": "varchar(255)",
          "unsigned": false,
          "autoincrement": false,
          "primary": false,
          "nullable": false,
          "unique": false,
          "length": 255,
          "precision": null,
          "scale": null,
          "default": null,
          "comment": null,
          "enumItems": [],
          "mappedType": "string"
        }
      },
      "name": "usuarios",
      "schema": "public",
      "indexes": [
        {
          "columnNames": [
            "id"
          ],
          "composite": false,
          "constraint": false,
          "keyName": "user_pkey",
          "unique": true,
          "primary": true
        }
      ],
      "checks": [],
      "foreignKeys": {},
      "nativeEnums": {},
      "comment": null
    }
  ],
  "nativeEnums": {}
}
